odoo/addons/ssi_inventory_closing_queue/README.rst
odoo/addons/ssi_inventory_closing_queue/__init__.py
odoo/addons/ssi_inventory_closing_queue/__manifest__.py
odoo/addons/ssi_inventory_closing_queue/data/base_automation_data.xml
odoo/addons/ssi_inventory_closing_queue/data/ir_actions_server_data.xml
odoo/addons/ssi_inventory_closing_queue/models/__init__.py
odoo/addons/ssi_inventory_closing_queue/models/inventory_closing.py
odoo/addons/ssi_inventory_closing_queue/static/description/icon.png
odoo14_addon_ssi_inventory_closing_queue-14.0.2.0.0.dist-info/METADATA
odoo14_addon_ssi_inventory_closing_queue-14.0.2.0.0.dist-info/WHEEL
odoo14_addon_ssi_inventory_closing_queue-14.0.2.0.0.dist-info/top_level.txt
odoo14_addon_ssi_inventory_closing_queue-14.0.2.0.0.dist-info/RECORD
